{
    "/js/main.js": "/js/main.js?id=76b884ce128a29010576",
    "/css/main.css": "/css/main.css?id=245d23b78bce0a0a17af",
    "/css/login.css": "/css/login.css?id=53b47f70821ddfa38a53",
    "/js/native.js": "/js/native.js?id=a0eee65e0a7c3a2ff9b6",
    "/js/vendors/redactor.js": "/js/vendors/redactor.js?id=4931265f8ebe3410f5fc",
    "/js/vendors/slim.kickstart.min.js": "/js/vendors/slim.kickstart.min.js?id=e5ef1948c4c668ba1188",
    "/css/vendors/slim.min.css": "/css/vendors/slim.min.css?id=f56b065aa610c65c2064"
}